{
  "Ardahan": {
    "don": 29.1,
    "don_seviye": "ORTA",
    "kuraklik": 28.1,
    "kuraklik_seviye": "ORTA",
    "yagis": 1.5,
    "yagis_seviye": "D횥힇횥K"
  },
  "Erzurum": {
    "don": 25.5,
    "don_seviye": "ORTA",
    "kuraklik": 27.4,
    "kuraklik_seviye": "ORTA",
    "yagis": 1.2,
    "yagis_seviye": "D횥힇횥K"
  },
  "Kars": {
    "don": 22.3,
    "don_seviye": "ORTA",
    "kuraklik": 30.7,
    "kuraklik_seviye": "ORTA",
    "yagis": 1.1,
    "yagis_seviye": "D횥힇횥K"
  },
  "Hakkari": {
    "don": 20.6,
    "don_seviye": "ORTA",
    "kuraklik": 28.3,
    "kuraklik_seviye": "ORTA",
    "yagis": 3.2,
    "yagis_seviye": "D횥힇횥K"
  },
  "Erzincan": {
    "don": 19.9,
    "don_seviye": "D횥힇횥K",
    "kuraklik": 27.8,
    "kuraklik_seviye": "ORTA",
    "yagis": 1.6,
    "yagis_seviye": "D횥힇횥K"
  },
  "G체m체힊hane": {
    "don": 19.8,
    "don_seviye": "D횥힇횥K",
    "kuraklik": 26.6,
    "kuraklik_seviye": "ORTA",
    "yagis": 1.5,
    "yagis_seviye": "D횥힇횥K"
  },
  "A휓r캇": {
    "don": 16.9,
    "don_seviye": "D횥힇횥K",
    "kuraklik": 29.5,
    "kuraklik_seviye": "ORTA",
    "yagis": 1.2,
    "yagis_seviye": "D횥힇횥K"
  },
  "Bayburt": {
    "don": 15.7,
    "don_seviye": "D횥힇횥K",
    "kuraklik": 27.2,
    "kuraklik_seviye": "ORTA",
    "yagis": 1.1,
    "yagis_seviye": "D횥힇횥K"
  },
  "Van": {
    "don": 15.7,
    "don_seviye": "D횥힇횥K",
    "kuraklik": 30.0,
    "kuraklik_seviye": "ORTA",
    "yagis": 1.1,
    "yagis_seviye": "D횥힇횥K"
  },
  "Bing철l": {
    "don": 12.8,
    "don_seviye": "D횥힇횥K",
    "kuraklik": 27.4,
    "kuraklik_seviye": "ORTA",
    "yagis": 2.6,
    "yagis_seviye": "D횥힇횥K"
  },
  "Mu힊": {
    "don": 11.5,
    "don_seviye": "D횥힇횥K",
    "kuraklik": 26.4,
    "kuraklik_seviye": "ORTA",
    "yagis": 2.7,
    "yagis_seviye": "D횥힇횥K"
  },
  "Bitlis": {
    "don": 11.1,
    "don_seviye": "D횥힇횥K",
    "kuraklik": 26.1,
    "kuraklik_seviye": "ORTA",
    "yagis": 2.7,
    "yagis_seviye": "D횥힇횥K"
  },
  "Artvin": {
    "don": 10.2,
    "don_seviye": "D횥힇횥K",
    "kuraklik": 24.5,
    "kuraklik_seviye": "ORTA",
    "yagis": 3.7,
    "yagis_seviye": "D횥힇횥K"
  },
  "Ni휓de": {
    "don": 8.8,
    "don_seviye": "D횥힇횥K",
    "kuraklik": 33.5,
    "kuraklik_seviye": "ORTA",
    "yagis": 0.9,
    "yagis_seviye": "D횥힇횥K"
  },
  "Sivas": {
    "don": 8.3,
    "don_seviye": "D횥힇횥K",
    "kuraklik": 31.0,
    "kuraklik_seviye": "ORTA",
    "yagis": 1.2,
    "yagis_seviye": "D횥힇횥K"
  },
  "Kayseri": {
    "don": 7.4,
    "don_seviye": "D횥힇횥K",
    "kuraklik": 35.3,
    "kuraklik_seviye": "ORTA",
    "yagis": 1.1,
    "yagis_seviye": "D횥힇횥K"
  },
  "I휓d캇r": {
    "don": 7.0,
    "don_seviye": "D횥힇횥K",
    "kuraklik": 35.6,
    "kuraklik_seviye": "ORTA",
    "yagis": 1.0,
    "yagis_seviye": "D횥힇횥K"
  },
  "Bolu": {
    "don": 6.4,
    "don_seviye": "D횥힇횥K",
    "kuraklik": 28.1,
    "kuraklik_seviye": "ORTA",
    "yagis": 1.9,
    "yagis_seviye": "D횥힇횥K"
  },
  "D체zce": {
    "don": 6.2,
    "don_seviye": "D횥힇횥K",
    "kuraklik": 28.7,
    "kuraklik_seviye": "ORTA",
    "yagis": 2.0,
    "yagis_seviye": "D횥힇횥K"
  },
  "Karab체k": {
    "don": 6.0,
    "don_seviye": "D횥힇횥K",
    "kuraklik": 28.0,
    "kuraklik_seviye": "ORTA",
    "yagis": 2.0,
    "yagis_seviye": "D횥힇횥K"
  },
  "Kastamonu": {
    "don": 5.6,
    "don_seviye": "D횥힇횥K",
    "kuraklik": 28.7,
    "kuraklik_seviye": "ORTA",
    "yagis": 1.2,
    "yagis_seviye": "D횥힇횥K"
  },
  "Tunceli": {
    "don": 5.5,
    "don_seviye": "D횥힇횥K",
    "kuraklik": 30.9,
    "kuraklik_seviye": "ORTA",
    "yagis": 1.9,
    "yagis_seviye": "D횥힇횥K"
  },
  "Nev힊ehir": {
    "don": 5.3,
    "don_seviye": "D횥힇횥K",
    "kuraklik": 36.0,
    "kuraklik_seviye": "ORTA",
    "yagis": 0.8,
    "yagis_seviye": "D횥힇횥K"
  },
  "Tokat": {
    "don": 5.1,
    "don_seviye": "D횥힇횥K",
    "kuraklik": 28.7,
    "kuraklik_seviye": "ORTA",
    "yagis": 1.6,
    "yagis_seviye": "D횥힇횥K"
  },
  "Yozgat": {
    "don": 4.9,
    "don_seviye": "D횥힇횥K",
    "kuraklik": 36.5,
    "kuraklik_seviye": "ORTA",
    "yagis": 1.0,
    "yagis_seviye": "D횥힇횥K"
  },
  "Ankara": {
    "don": 4.8,
    "don_seviye": "D횥힇횥K",
    "kuraklik": 37.9,
    "kuraklik_seviye": "ORTA",
    "yagis": 1.0,
    "yagis_seviye": "D횥힇횥K"
  },
  "Afyonkarahisar": {
    "don": 4.8,
    "don_seviye": "D횥힇횥K",
    "kuraklik": 36.5,
    "kuraklik_seviye": "ORTA",
    "yagis": 0.9,
    "yagis_seviye": "D횥힇횥K"
  },
  "Bilecik": {
    "don": 4.4,
    "don_seviye": "D횥힇횥K",
    "kuraklik": 33.3,
    "kuraklik_seviye": "ORTA",
    "yagis": 1.2,
    "yagis_seviye": "D횥힇횥K"
  },
  "횉ank캇r캇": {
    "don": 4.3,
    "don_seviye": "D횥힇횥K",
    "kuraklik": 37.3,
    "kuraklik_seviye": "ORTA",
    "yagis": 0.8,
    "yagis_seviye": "D횥힇횥K"
  },
  "K캇r캇kkale": {
    "don": 4.2,
    "don_seviye": "D횥힇횥K",
    "kuraklik": 38.1,
    "kuraklik_seviye": "ORTA",
    "yagis": 0.8,
    "yagis_seviye": "D횥힇횥K"
  },
  "횉orum": {
    "don": 4.2,
    "don_seviye": "D횥힇횥K",
    "kuraklik": 33.1,
    "kuraklik_seviye": "ORTA",
    "yagis": 1.1,
    "yagis_seviye": "D횥힇횥K"
  },
  "Eski힊ehir": {
    "don": 4.0,
    "don_seviye": "D횥힇횥K",
    "kuraklik": 34.7,
    "kuraklik_seviye": "ORTA",
    "yagis": 0.8,
    "yagis_seviye": "D횥힇횥K"
  },
  "K캇r힊ehir": {
    "don": 3.9,
    "don_seviye": "D횥힇횥K",
    "kuraklik": 37.8,
    "kuraklik_seviye": "ORTA",
    "yagis": 0.8,
    "yagis_seviye": "D횥힇횥K"
  },
  "힇캇rnak": {
    "don": 3.9,
    "don_seviye": "D횥힇횥K",
    "kuraklik": 30.7,
    "kuraklik_seviye": "ORTA",
    "yagis": 2.8,
    "yagis_seviye": "D횥힇횥K"
  },
  "K체tahya": {
    "don": 3.9,
    "don_seviye": "D횥힇횥K",
    "kuraklik": 35.2,
    "kuraklik_seviye": "ORTA",
    "yagis": 1.2,
    "yagis_seviye": "D횥힇횥K"
  },
  "Bart캇n": {
    "don": 3.7,
    "don_seviye": "D횥힇횥K",
    "kuraklik": 30.2,
    "kuraklik_seviye": "ORTA",
    "yagis": 1.7,
    "yagis_seviye": "D횥힇횥K"
  },
  "Sakarya": {
    "don": 3.7,
    "don_seviye": "D횥힇횥K",
    "kuraklik": 30.9,
    "kuraklik_seviye": "ORTA",
    "yagis": 1.8,
    "yagis_seviye": "D횥힇횥K"
  },
  "Konya": {
    "don": 3.7,
    "don_seviye": "D횥힇횥K",
    "kuraklik": 37.9,
    "kuraklik_seviye": "ORTA",
    "yagis": 0.9,
    "yagis_seviye": "D횥힇횥K"
  },
  "K캇rklareli": {
    "don": 3.7,
    "don_seviye": "D횥힇횥K",
    "kuraklik": 36.1,
    "kuraklik_seviye": "ORTA",
    "yagis": 0.9,
    "yagis_seviye": "D횥힇횥K"
  },
  "Kocaeli": {
    "don": 3.4,
    "don_seviye": "D횥힇횥K",
    "kuraklik": 30.1,
    "kuraklik_seviye": "ORTA",
    "yagis": 1.8,
    "yagis_seviye": "D횥힇횥K"
  },
  "Edirne": {
    "don": 3.4,
    "don_seviye": "D횥힇횥K",
    "kuraklik": 39.2,
    "kuraklik_seviye": "ORTA",
    "yagis": 0.8,
    "yagis_seviye": "D횥힇횥K"
  },
  "Siirt": {
    "don": 3.2,
    "don_seviye": "D횥힇횥K",
    "kuraklik": 30.5,
    "kuraklik_seviye": "ORTA",
    "yagis": 2.5,
    "yagis_seviye": "D횥힇횥K"
  },
  "Isparta": {
    "don": 3.1,
    "don_seviye": "D횥힇횥K",
    "kuraklik": 33.5,
    "kuraklik_seviye": "ORTA",
    "yagis": 1.6,
    "yagis_seviye": "D횥힇횥K"
  },
  "Malatya": {
    "don": 3.1,
    "don_seviye": "D횥힇횥K",
    "kuraklik": 35.1,
    "kuraklik_seviye": "ORTA",
    "yagis": 1.4,
    "yagis_seviye": "D횥힇횥K"
  },
  "Aksaray": {
    "don": 3.1,
    "don_seviye": "D횥힇횥K",
    "kuraklik": 38.5,
    "kuraklik_seviye": "ORTA",
    "yagis": 0.8,
    "yagis_seviye": "D횥힇횥K"
  },
  "횉anakkale": {
    "don": 2.9,
    "don_seviye": "D횥힇횥K",
    "kuraklik": 35.8,
    "kuraklik_seviye": "ORTA",
    "yagis": 1.4,
    "yagis_seviye": "D횥힇횥K"
  },
  "Elaz캇휓": {
    "don": 2.9,
    "don_seviye": "D횥힇횥K",
    "kuraklik": 31.4,
    "kuraklik_seviye": "ORTA",
    "yagis": 1.9,
    "yagis_seviye": "D횥힇횥K"
  },
  "Amasya": {
    "don": 2.9,
    "don_seviye": "D횥힇횥K",
    "kuraklik": 32.2,
    "kuraklik_seviye": "ORTA",
    "yagis": 1.0,
    "yagis_seviye": "D횥힇횥K"
  },
  "Bursa": {
    "don": 2.8,
    "don_seviye": "D횥힇횥K",
    "kuraklik": 31.6,
    "kuraklik_seviye": "ORTA",
    "yagis": 1.9,
    "yagis_seviye": "D횥힇횥K"
  },
  "U힊ak": {
    "don": 2.8,
    "don_seviye": "D횥힇횥K",
    "kuraklik": 38.1,
    "kuraklik_seviye": "ORTA",
    "yagis": 1.0,
    "yagis_seviye": "D횥힇횥K"
  },
  "Burdur": {
    "don": 2.8,
    "don_seviye": "D횥힇횥K",
    "kuraklik": 35.5,
    "kuraklik_seviye": "ORTA",
    "yagis": 1.2,
    "yagis_seviye": "D횥힇횥K"
  },
  "Hatay": {
    "don": 2.6,
    "don_seviye": "D횥힇횥K",
    "kuraklik": 32.4,
    "kuraklik_seviye": "ORTA",
    "yagis": 2.1,
    "yagis_seviye": "D횥힇횥K"
  },
  "Karaman": {
    "don": 2.6,
    "don_seviye": "D횥힇횥K",
    "kuraklik": 38.4,
    "kuraklik_seviye": "ORTA",
    "yagis": 0.7,
    "yagis_seviye": "D횥힇횥K"
  },
  "Bal캇kesir": {
    "don": 2.6,
    "don_seviye": "D횥힇횥K",
    "kuraklik": 37.2,
    "kuraklik_seviye": "ORTA",
    "yagis": 1.2,
    "yagis_seviye": "D횥힇횥K"
  },
  "Mu휓la": {
    "don": 2.5,
    "don_seviye": "D횥힇횥K",
    "kuraklik": 36.7,
    "kuraklik_seviye": "ORTA",
    "yagis": 1.7,
    "yagis_seviye": "D횥힇횥K"
  },
  "Diyarbak캇r": {
    "don": 2.5,
    "don_seviye": "D횥힇횥K",
    "kuraklik": 32.9,
    "kuraklik_seviye": "ORTA",
    "yagis": 2.2,
    "yagis_seviye": "D횥힇횥K"
  },
  "Manisa": {
    "don": 2.5,
    "don_seviye": "D횥힇횥K",
    "kuraklik": 38.4,
    "kuraklik_seviye": "ORTA",
    "yagis": 1.6,
    "yagis_seviye": "D횥힇횥K"
  },
  "Batman": {
    "don": 2.5,
    "don_seviye": "D횥힇횥K",
    "kuraklik": 32.6,
    "kuraklik_seviye": "ORTA",
    "yagis": 2.2,
    "yagis_seviye": "D횥힇횥K"
  },
  "Osmaniye": {
    "don": 2.4,
    "don_seviye": "D횥힇횥K",
    "kuraklik": 32.9,
    "kuraklik_seviye": "ORTA",
    "yagis": 2.0,
    "yagis_seviye": "D횥힇횥K"
  },
  "Samsun": {
    "don": 2.4,
    "don_seviye": "D횥힇횥K",
    "kuraklik": 29.6,
    "kuraklik_seviye": "ORTA",
    "yagis": 1.7,
    "yagis_seviye": "D횥힇횥K"
  },
  "Ad캇yaman": {
    "don": 2.4,
    "don_seviye": "D횥힇횥K",
    "kuraklik": 34.0,
    "kuraklik_seviye": "ORTA",
    "yagis": 2.1,
    "yagis_seviye": "D횥힇횥K"
  },
  "Tekirda휓": {
    "don": 2.1,
    "don_seviye": "D횥힇횥K",
    "kuraklik": 36.2,
    "kuraklik_seviye": "ORTA",
    "yagis": 0.9,
    "yagis_seviye": "D횥힇횥K"
  },
  "Zonguldak": {
    "don": 2.1,
    "don_seviye": "D횥힇횥K",
    "kuraklik": 28.2,
    "kuraklik_seviye": "ORTA",
    "yagis": 1.7,
    "yagis_seviye": "D횥힇횥K"
  },
  "Yalova": {
    "don": 2.1,
    "don_seviye": "D횥힇횥K",
    "kuraklik": 30.4,
    "kuraklik_seviye": "ORTA",
    "yagis": 1.6,
    "yagis_seviye": "D횥힇횥K"
  },
  "Mardin": {
    "don": 2.1,
    "don_seviye": "D횥힇횥K",
    "kuraklik": 35.6,
    "kuraklik_seviye": "ORTA",
    "yagis": 1.6,
    "yagis_seviye": "D횥힇횥K"
  },
  "Sinop": {
    "don": 2.1,
    "don_seviye": "D횥힇횥K",
    "kuraklik": 26.5,
    "kuraklik_seviye": "ORTA",
    "yagis": 1.4,
    "yagis_seviye": "D횥힇횥K"
  },
  "힇anl캇urfa": {
    "don": 2.1,
    "don_seviye": "D횥힇횥K",
    "kuraklik": 35.6,
    "kuraklik_seviye": "ORTA",
    "yagis": 1.8,
    "yagis_seviye": "D횥힇횥K"
  },
  "Ayd캇n": {
    "don": 2.0,
    "don_seviye": "D횥힇횥K",
    "kuraklik": 39.3,
    "kuraklik_seviye": "ORTA",
    "yagis": 1.4,
    "yagis_seviye": "D횥힇횥K"
  },
  "Trabzon": {
    "don": 2.0,
    "don_seviye": "D횥힇횥K",
    "kuraklik": 23.8,
    "kuraklik_seviye": "ORTA",
    "yagis": 2.6,
    "yagis_seviye": "D횥힇횥K"
  },
  "Kilis": {
    "don": 2.0,
    "don_seviye": "D횥힇횥K",
    "kuraklik": 36.6,
    "kuraklik_seviye": "ORTA",
    "yagis": 1.4,
    "yagis_seviye": "D횥힇횥K"
  },
  "Rize": {
    "don": 2.0,
    "don_seviye": "D횥힇횥K",
    "kuraklik": 24.4,
    "kuraklik_seviye": "ORTA",
    "yagis": 2.7,
    "yagis_seviye": "D횥힇횥K"
  },
  "Kahramanmara힊": {
    "don": 2.0,
    "don_seviye": "D횥힇횥K",
    "kuraklik": 36.4,
    "kuraklik_seviye": "ORTA",
    "yagis": 1.6,
    "yagis_seviye": "D횥힇횥K"
  },
  "Gaziantep": {
    "don": 2.0,
    "don_seviye": "D횥힇횥K",
    "kuraklik": 36.2,
    "kuraklik_seviye": "ORTA",
    "yagis": 1.6,
    "yagis_seviye": "D횥힇횥K"
  },
  "Denizli": {
    "don": 1.9,
    "don_seviye": "D횥힇횥K",
    "kuraklik": 40.7,
    "kuraklik_seviye": "Y횥KSEK",
    "yagis": 1.0,
    "yagis_seviye": "D횥힇횥K"
  },
  "캅stanbul": {
    "don": 1.8,
    "don_seviye": "D횥힇횥K",
    "kuraklik": 31.5,
    "kuraklik_seviye": "ORTA",
    "yagis": 1.4,
    "yagis_seviye": "D횥힇횥K"
  },
  "Giresun": {
    "don": 1.8,
    "don_seviye": "D횥힇횥K",
    "kuraklik": 27.2,
    "kuraklik_seviye": "ORTA",
    "yagis": 2.4,
    "yagis_seviye": "D횥힇횥K"
  },
  "캅zmir": {
    "don": 1.8,
    "don_seviye": "D횥힇횥K",
    "kuraklik": 39.5,
    "kuraklik_seviye": "ORTA",
    "yagis": 1.6,
    "yagis_seviye": "D횥힇횥K"
  },
  "Ordu": {
    "don": 1.8,
    "don_seviye": "D횥힇횥K",
    "kuraklik": 26.6,
    "kuraklik_seviye": "ORTA",
    "yagis": 2.4,
    "yagis_seviye": "D횥힇횥K"
  },
  "Antalya": {
    "don": 1.6,
    "don_seviye": "D횥힇횥K",
    "kuraklik": 37.5,
    "kuraklik_seviye": "ORTA",
    "yagis": 2.3,
    "yagis_seviye": "D횥힇횥K"
  },
  "Adana": {
    "don": 1.5,
    "don_seviye": "D횥힇횥K",
    "kuraklik": 38.8,
    "kuraklik_seviye": "ORTA",
    "yagis": 1.5,
    "yagis_seviye": "D횥힇횥K"
  },
  "Mersin": {
    "don": 1.0,
    "don_seviye": "D횥힇횥K",
    "kuraklik": 28.9,
    "kuraklik_seviye": "ORTA",
    "yagis": 1.3,
    "yagis_seviye": "D횥힇횥K"
  }
}